{
  "_fv": 85,
  "_type": "recipe",
  "definition": {
    "recipeType": "Crafting",
    "recipeRetstackSize": 1,
    "group": "undertale",
    "unlockingItems": [
      {
        "value": "Items.DIAMOND"
      }
    ],
    "cookingBookCategory": "MISC",
    "xpReward": 0.0,
    "cookingTime": 200,
    "craftingBookCategory": "MISC",
    "recipeShapeless": false,
    "recipeSlots": [
      {
        "value": ""
      },
      {
        "value": "Items.EXPERIENCE_BOTTLE"
      },
      {
        "value": ""
      },
      {
        "value": "Items.EMERALD"
      },
      {
        "value": "Items.DIAMOND"
      },
      {
        "value": "Items.EMERALD"
      },
      {
        "value": ""
      },
      {
        "value": "Items.EMERALD"
      },
      {
        "value": ""
      }
    ],
    "recipeReturnStack": {
      "value": "CUSTOM:Magicstone"
    },
    "name": "potral",
    "namespace": "mod"
  }
}